oshino_zmq/__init__.py
oshino_zmq/agent.py
oshino_zmq/version.py
oshino_zmq-0.1.6.dist-info/DESCRIPTION.rst
oshino_zmq-0.1.6.dist-info/METADATA
oshino_zmq-0.1.6.dist-info/RECORD
oshino_zmq-0.1.6.dist-info/WHEEL
oshino_zmq-0.1.6.dist-info/metadata.json
oshino_zmq-0.1.6.dist-info/top_level.txt
